odoo9_addon_l10n_fr_state-9.0.0.1.1.99.dev8-py2.7-nspkg.pth
odoo9_addon_l10n_fr_state-9.0.0.1.1.99.dev8.dist-info/DESCRIPTION.rst
odoo9_addon_l10n_fr_state-9.0.0.1.1.99.dev8.dist-info/METADATA
odoo9_addon_l10n_fr_state-9.0.0.1.1.99.dev8.dist-info/RECORD
odoo9_addon_l10n_fr_state-9.0.0.1.1.99.dev8.dist-info/WHEEL
odoo9_addon_l10n_fr_state-9.0.0.1.1.99.dev8.dist-info/metadata.json
odoo9_addon_l10n_fr_state-9.0.0.1.1.99.dev8.dist-info/namespace_packages.txt
odoo9_addon_l10n_fr_state-9.0.0.1.1.99.dev8.dist-info/top_level.txt
odoo_addons/l10n_fr_state/README.rst
odoo_addons/l10n_fr_state/__init__.py
odoo_addons/l10n_fr_state/__openerp__.py
odoo_addons/l10n_fr_state/data/res_country_state_data.yml
odoo_addons/l10n_fr_state/i18n/fr.po
odoo_addons/l10n_fr_state/migrations/9.0.0.1.1/post-migration.py
odoo_addons/l10n_fr_state/migrations/9.0.0.1.1/pre-migration.py
odoo_addons/l10n_fr_state/static/description/icon.png
odoo_addons/l10n_fr_state/static/src/img/screenshots/1.png
